debbuild/__init__.py
debbuild/__main__.py
debbuild/tests/test_debbuild.py
debbuild-0.2.2.dist-info/licenses/LICENSE
debbuild-0.2.2.dist-info/METADATA
debbuild-0.2.2.dist-info/WHEEL
debbuild-0.2.2.dist-info/entry_points.txt
debbuild-0.2.2.dist-info/top_level.txt
debbuild-0.2.2.dist-info/RECORD
