Metadata-Version: 2.4
Name: debbuild
Version: 0.2.2
Summary: Command line utility to build Deb package without Debian
Author-email: "IKUS Software inc." <support@ikus-soft.com>
License: Copyright (c) 2014 Alastair Houghton
Project-URL: Homepage, https://gitlab.com/ikus-soft/debbuild
Project-URL: source, https://gitlab.com/ikus-soft/debbuild
Project-URL: bug_tracker, https://gitlab.com/ikus-soft/debbuild/-/issues
Classifier: Development Status :: 4 - Beta
Classifier: License :: OSI Approved :: MIT License
Classifier: Programming Language :: Python :: 3
Classifier: Programming Language :: Python :: 3.7
Classifier: Programming Language :: Python :: 3.8
Classifier: Programming Language :: Python :: 3.9
Classifier: Programming Language :: Python :: 3.10
Classifier: Programming Language :: Python :: 3.11
Classifier: Programming Language :: Python :: 3.12
Classifier: Programming Language :: Python :: 3 :: Only
Classifier: Topic :: Desktop Environment
Requires-Python: <4,>=3.6
License-File: LICENSE
Requires-Dist: Jinja2<4,>=2.10
Requires-Dist: unix_ar
Provides-Extra: test
Requires-Dist: pytest; extra == "test"
Dynamic: license-file
